LICENSE
README.md
setup.py
config/__init__.py
core/__init__.py
rhains.egg-info/PKG-INFO
rhains.egg-info/SOURCES.txt
rhains.egg-info/dependency_links.txt
rhains.egg-info/top_level.txt
security/__init__.py
services/__init__.py
utils/__init__.py